linetasker/__init__.py
linetasker/core.py
linetasker/main.py
linetasker/main_typer.py
linetasker/task.py
linetasker/utils/__init__.py
linetasker/utils/levelbar.py
linetasker/utils/logging.py
linetasker/utils/prettier.py
linetasker-0.1.0.dist-info/METADATA
linetasker-0.1.0.dist-info/WHEEL
linetasker-0.1.0.dist-info/RECORD
