Metadata-Version: 2.1
Name: linetasker
Version: 0.1.0
Summary: 
Author: Anthony
Author-email: benjaraf006@gmail.com
Requires-Python: >=3.10,<4.0
Classifier: Programming Language :: Python :: 3
Classifier: Programming Language :: Python :: 3.10
Classifier: Programming Language :: Python :: 3.11
Requires-Dist: click (>=8.1.3,<9.0.0)
Requires-Dist: rich (>=13.3.5,<14.0.0)
Requires-Dist: typer[all] (>=0.9.0,<0.10.0)
